<featureType>
  <id>FeatureTypeInfoImpl-76ff99a:17931091a82:-7fe9</id>
  <name>ka_bauinventarobj</name>
  <nativeName>ka_bauinventarobj</nativeName>
  <namespace>
    <id>NamespaceInfoImpl--baf9b6e:17930f5e8f5:-7ffb</id>
  </namespace>
  <title>ka_bauinventarobj</title>
  <keywords>
    <string>features</string>
    <string>ka_bauinventarobj</string>
  </keywords>
  <nativeCRS class="projected">PROJCS[&quot;CH1903+ / LV95&quot;, 
  GEOGCS[&quot;CH1903+&quot;, 
    DATUM[&quot;CH1903+&quot;, 
      SPHEROID[&quot;Bessel 1841&quot;, 6377397.155, 299.1528128, AUTHORITY[&quot;EPSG&quot;,&quot;7004&quot;]], 
      TOWGS84[674.374, 15.056, 405.346, 0.0, 0.0, 0.0, 0.0], 
      AUTHORITY[&quot;EPSG&quot;,&quot;6150&quot;]], 
    PRIMEM[&quot;Greenwich&quot;, 0.0, AUTHORITY[&quot;EPSG&quot;,&quot;8901&quot;]], 
    UNIT[&quot;degree&quot;, 0.017453292519943295], 
    AXIS[&quot;Geodetic longitude&quot;, EAST], 
    AXIS[&quot;Geodetic latitude&quot;, NORTH], 
    AUTHORITY[&quot;EPSG&quot;,&quot;4150&quot;]], 
  PROJECTION[&quot;Oblique_Mercator&quot;, AUTHORITY[&quot;EPSG&quot;,&quot;9815&quot;]], 
  PARAMETER[&quot;longitude_of_center&quot;, 7.439583333333333], 
  PARAMETER[&quot;latitude_of_center&quot;, 46.952405555555565], 
  PARAMETER[&quot;azimuth&quot;, 90.0], 
  PARAMETER[&quot;scale_factor&quot;, 1.0], 
  PARAMETER[&quot;false_easting&quot;, 2600000.0], 
  PARAMETER[&quot;false_northing&quot;, 1200000.0], 
  PARAMETER[&quot;rectified_grid_angle&quot;, 90.0], 
  UNIT[&quot;m&quot;, 1.0], 
  AXIS[&quot;Easting&quot;, EAST], 
  AXIS[&quot;Northing&quot;, NORTH], 
  AUTHORITY[&quot;EPSG&quot;,&quot;2056&quot;]]</nativeCRS>
  <srs>EPSG:2056</srs>
  <nativeBoundingBox>
    <minx>2620798.0</minx>
    <maxx>2675519.0</maxx>
    <miny>1221399.0</miny>
    <maxy>1273500.0</maxy>
    <crs class="projected">EPSG:2056</crs>
  </nativeBoundingBox>
  <latLonBoundingBox>
    <minx>7.7128152585102745</minx>
    <maxx>8.442960473135676</maxx>
    <miny>47.139262226186446</miny>
    <maxy>47.61184713340607</maxy>
    <crs>EPSG:4326</crs>
  </latLonBoundingBox>
  <projectionPolicy>FORCE_DECLARED</projectionPolicy>
  <enabled>true</enabled>
  <store class="dataStore">
    <id>DataStoreInfoImpl--baf9b6e:17930f5e8f5:-7ff9</id>
  </store>
  <serviceConfiguration>false</serviceConfiguration>
  <maxFeatures>0</maxFeatures>
  <numDecimals>0</numDecimals>
  <padWithZeros>false</padWithZeros>
  <forcedDecimal>false</forcedDecimal>
  <overridingServiceSRS>false</overridingServiceSRS>
  <skipNumberMatched>false</skipNumberMatched>
  <circularArcPresent>false</circularArcPresent>
</featureType>